lib_defender/__init__.py
lib_defender/core.py
lib_defender-0.9.0.dist-info/LICENSE
lib_defender-0.9.0.dist-info/METADATA
lib_defender-0.9.0.dist-info/WHEEL
lib_defender-0.9.0.dist-info/top_level.txt
lib_defender-0.9.0.dist-info/RECORD
